LICENSE
MANIFEST.in
README.md
setup.py
haeidbvwjy/__init__.py
haeidbvwjy/api_helper.py
haeidbvwjy/configuration.py
haeidbvwjy/decorators.py
haeidbvwjy/haeidbvwjy_client.py
haeidbvwjy.egg-info/PKG-INFO
haeidbvwjy.egg-info/SOURCES.txt
haeidbvwjy.egg-info/dependency_links.txt
haeidbvwjy.egg-info/requires.txt
haeidbvwjy.egg-info/top_level.txt
haeidbvwjy/controllers/__init__.py
haeidbvwjy/controllers/api_controller.py
haeidbvwjy/controllers/base_controller.py
haeidbvwjy/exceptions/__init__.py
haeidbvwjy/exceptions/api_exception.py
haeidbvwjy/http/__init__.py
haeidbvwjy/http/http_call_back.py
haeidbvwjy/http/http_client.py
haeidbvwjy/http/http_context.py
haeidbvwjy/http/http_method_enum.py
haeidbvwjy/http/http_request.py
haeidbvwjy/http/http_response.py
haeidbvwjy/http/requests_client.py
haeidbvwjy/http/auth/__init__.py
haeidbvwjy/http/auth/basic_auth.py
haeidbvwjy/models/__init__.py
haeidbvwjy/models/suite_code_enum.py
tests/__init__.py
tests/http_response_catcher.py
tests/test_helper.py
tests/controllers/__init__.py
tests/controllers/controller_test_base.py
tests/controllers/test_api_controller.py